README.rst
setup.py
python_sms_gateway/__init__.py
python_sms_gateway.egg-info/PKG-INFO
python_sms_gateway.egg-info/SOURCES.txt
python_sms_gateway.egg-info/dependency_links.txt
python_sms_gateway.egg-info/not-zip-safe
python_sms_gateway.egg-info/top_level.txt
python_sms_gateway/nexmo/__init__.py