Metadata-Version: 1.0
Name: python-sms-gateway
Version: 0.0.2
Summary: Python SMS Gateway is module used to send text sms.
Home-page: https://github.com/muhilvarnan/python_sms_gateway
Author: muhilvarnan
Author-email: muhilvarnan.v@gmail.com
License: MIT
Platform: UNKNOWN
